is_domain_free/__init__.py
is_domain_free/base.py
is_domain_free/exceptions.py
is_domain_free/tests/__init__.py
is_domain_free/tests/tests.py
is_domain_free-0.0.1.dist-info/METADATA
is_domain_free-0.0.1.dist-info/RECORD
is_domain_free-0.0.1.dist-info/WHEEL
is_domain_free-0.0.1.dist-info/top_level.txt
