Metadata-Version: 2.1
Name: is-domain-free
Version: 0.0.1
Summary: Simple package to check if 1 or more domain names are available.
Home-page: https://github.com/mogosselin/is_domain_free
Author: Marc-Olivier Gosselin
Author-email: mogosselin@gmail.com
License: UNKNOWN
Platform: UNKNOWN
Classifier: Programming Language :: Python :: 3
Classifier: License :: OSI Approved :: MIT License
Classifier: Operating System :: OS Independent
